.DS_Store
yitest/__init__.py
yitest-0.3.dist-info/METADATA
yitest-0.3.dist-info/RECORD
yitest-0.3.dist-info/WHEEL
yitest-0.3.dist-info/top_level.txt
