Metadata-Version: 2.1
Name: yitest
Version: 0.3
Summary: The funniest joke in the world
Home-page: https://github.com/dymodi/machine_learning
Author: yi
Author-email: dymodi@gmail.com
License: MIT
Platform: UNKNOWN
